[{"title":"Arniston memoirs","author":null,"year":null,"url":"http:\/\/digital.nls.uk\/95163602","placename":"Home Farm","snippet":"SIR JAMES DUNDAS, GOVERNOR OF BERWICK. PAGE His birth and education, ..... 5 His marriages, ...... 5 Purchases of land by Sir James Dundas, . . . f) Arniston Burial-place at Borthwick Church, . . 6 Agricultural improvements, .... 8 The Home Farm at Arniston in 1628, . . . 10 Servants' wages, . . . . . .11 Death of Sir James Dundas, . . . . 12 His will and funeral, . . . . .12 CHAPTER III. THE FIRST LORD ARNISTON.    "}]