[{"title":"Hit and Run","author":"Johnstone, Doug","year":null,"url":null,"placename":"The Inch","snippet":"He turned left and headed south. He followed the plumes of black smoke, down Minto Street and past Cameron Toll, until he was at The Inch. Didn't take long, but his phone rang four times.    "},{"title":"Hit and Run","author":"Johnstone, Doug","year":null,"url":null,"placename":"The Inch","snippet":"'Looks like something's burning, out near The Inch.'    "},{"title":"Hit and Run","author":"Johnstone, Doug","year":null,"url":null,"placename":"The Inch","snippet":"'Did you say The Inch?'    "},{"title":"Hit and Run","author":"Johnstone, Doug","year":null,"url":null,"placename":"The Inch","snippet":"'Is that in The Inch?'    "}]