[{"title":"Bog-Myrtle and Peat; Tales Chiefly of Galloway Gathered from the Years 1889 to 1895","author":"Crockett, S. R. (Samuel Rutherford)","year":null,"url":"http:\/\/www.gutenberg.org\/ebooks\/13667","placename":"Glaisters","snippet":"\"Na, na,\" said Simeon Gleg; \"I mean Maister Golder o' the Glaisters.    "},{"title":"Bog-Myrtle and Peat; Tales Chiefly of Galloway Gathered from the Years 1889 to 1895","author":"Crockett, S. R. (Samuel Rutherford)","year":null,"url":"http:\/\/www.gutenberg.org\/ebooks\/13667","placename":"Glaisters","snippet":"\"Na, na,\" said Simeon Gleg; \"I mean Maister Golder o' the Glaisters.    "},{"title":"Bog-Myrtle and Peat. Tales, chiefly of Galloway, gathered from the years 1889 to 1895","author":"Crockett, Samuel Rutherford.","year":"1895-01-01","url":"https:\/\/historicaltexts.jisc.ac.uk\/bl-000821611","placename":"Glaisters","snippet":"\" Na, na,\" said Simeon Gleg; \" I mean MaisterGolder o' the Glaisters.    "}]