[{"title":"Black's picturesque tourist of Scotland.","author":null,"year":"1857-01-01","url":"http:\/\/babel.hathitrust.org\/cgi\/pt?id=uc2.ark:\/13960\/t9862nx30","placename":"Grahamslaw","snippet":"* From Kelso a road leads to Jed1)urgh, by tlio villnges of Maxwillhcugli and Heaton, the beautiful banks of the Kale, Grahamslaw, wliere there are sonie remarkable  caves, the villages of Eekford and Crailing, Crailing House (J. Taton, Esq.), fornierlv the scat of the noble familv of Craustouii, and Bonjed\u00ab;ird.    "}]