[{"title":"Miscellaneous Prose Works of Sir Walter Scott, Bart","author":"Scott, Walter","year":"1847-01-01","url":"https:\/\/historicaltexts.jisc.ac.uk\/bl-003316905-01","placename":"Glengelt","snippet":"executed August 1st, 1538, there arecomprehended the Moat of Lochquarret, the castleof the same, called the Castle of Borthwick ; halfof Bateland, in the county of Edinburgh; Borthwick, in Selkirkshire ; Legerwood, Glengelt, Colinlaw, and Brownhouse, in Berwickshire ; Ormiston,Herriot, Herriotmuir, Hethpule, and Whitfield, inthe county of Peebles; aud Aberdour, in Aberdeenshire ; which lands, by this deed are destinedto William, Lord of Borthwick ; John Borthwick,his son and apparent heir; Sir John Borthwick ofGordonhall; and William Borthwick of Crookstone,and their heirs-male respectively.    "}]