[{"title":"Black's picturesque tourist of Scotland.","author":null,"year":"1857-01-01","url":"http:\/\/babel.hathitrust.org\/cgi\/pt?id=uc2.ark:\/13960\/t9862nx30","placename":"The Square","snippet":"Recently, with the exception of the great hall, it has been almost totally renewed. The Square, of which it forms a part, was at one time surrounded with the shops of tradesmen, all ot which perished in the destructive fires of 1824. The entrance to the courts is at the south-west angle of the square.    "}]