[{"title":"Two gray tourists: from papers of Mr. Philemon Perch","author":"Johnston, Richard Malcolm","year":"1893-01-01","url":"http:\/\/babel.hathitrust.org\/cgi\/pt?id=loc.ark:\/13960\/t8mc9s460","placename":"Morocco Land","snippet":"This announcement served to divert my thoughts from the pathway in which they had been traveling, and soon afterwards my friend and I went in search of sleep and found it. After early breakfast we took a carriage and drove into old town, High street, Netherbow, and Canongate, passing slowly along, through Morocco Land, full of romantic traditions, St. Anne's Yards, the Debtors' Sanctuary, made so widely known by the Chronicles of the Canongate, Queen Mary's Garden, near where Rizzio    "}]