[{"title":"Art Rambles in the Highlands and Islands of Scotland ... With ... sketches, etc","author":"Reid, John T.","year":"1878-01-01","url":"https:\/\/historicaltexts.jisc.ac.uk\/bl-003065635","placename":"Mortimer'S Deep","snippet":"Somejoined the bathers at the \" silver beach;\" yachters looked out for the \" MaryJane,\" the \" Bertha,\" or the \" Star,\" and were soon cruising at will over thewaters; many took to the small boats and steered towards Inchcolm,* listenedto the boatman's tale about \" Mortimer's Deep,\" where a company of monksdrowned the sailors who attempted to convey for interment in a barge theremains of Mortimer, between the island and Aberdour; they explored theruins of the abbey founded by Alexander I., and were refreshed by a drink ofgood new milk they got at the shepherd's house; others visited the picturesqueruins of old Aberdour Castle.    "}]