[{"title":"Miscellaneous Prose Works of Sir Walter Scott, Bart","author":"Scott, Walter","year":"1847-01-01","url":"https:\/\/historicaltexts.jisc.ac.uk\/bl-003316905-01","placename":"Kirkhill","snippet":"This ancient and stately tower rises out of thecentre of a small, but well-cultivated valley, watered by a stream called the Gore, which, flowing tothe north-eastward, joins the Esk near Kirkhill;thus deceiving the eye of the spectator, who is ledto imagine it the same brook with that on whichCrichton Castle is situated at about two miles distance, and which has a south-easterly course.    "}]